trame/__init__.py
trame/modules/__init__.py
trame/modules/gantt.py
trame/widgets/__init__.py
trame/widgets/gantt.py
trame_gantt/__init__.py
trame_gantt/module/__init__.py
trame_gantt/module/serve/style.css
trame_gantt/module/serve/trame-gantt.umd.js
trame_gantt/widgets/__init__.py
trame_gantt/widgets/gantt.py
trame_gantt-0.1.5.dist-info/LICENSE
trame_gantt-0.1.5.dist-info/METADATA
trame_gantt-0.1.5.dist-info/WHEEL
trame_gantt-0.1.5.dist-info/top_level.txt
trame_gantt-0.1.5.dist-info/RECORD
